{
    "background": "210 40% 98%",
    "foreground": "222 47% 11%",
    "card": "0 0% 100%",
    "card-foreground": "222 47% 11%",
    "primary": "200 90% 45%",
    "primary-foreground": "0 0% 100%",
    "secondary": "180 50% 90%",
    "secondary-foreground": "200 90% 20%",
    "muted": "210 40% 96%",
    "muted-foreground": "215 20% 40%",
    "accent": "170 60% 45%",
    "accent-foreground": "0 0% 100%",
    "destructive": "0 85% 60%",
    "destructive-foreground": "0 0% 100%",
    "popover": "0 0% 100%",
    "popover-foreground": "222 47% 11%",
    "border": "210 20% 85%",
    "input": "210 20% 90%",
    "ring": "200 90% 45%",
    "chart-1": "200 80% 45%",
    "chart-2": "160 60% 40%",
    "chart-3": "40 90% 55%",
    "chart-4": "280 60% 55%",
    "chart-5": "340 70% 55%",
    "sidebar": "200 90% 45%",
    "sidebar-foreground": "0 0% 100%",
    "sidebar-accent": "170 60% 45%",
    "sidebar-accent-foreground": "0 0% 100%",
    "sidebar-border": "210 20% 85%",
    "sidebar-ring": "200 90% 45%"
}
